dhanhq_utils-0.1.0.dist-info/METADATA
dhanhq_utils-0.1.0.dist-info/WHEEL
dhanhq_utils-0.1.0.dist-info/licenses/LICENSE
dhanhq_utils.libs/libgcc_s-98a1ef30.so.1
dhanhq_utils/__init__.py
dhanhq_utils/dhanhq_utils.cpython-313-x86_64-linux-musl.so
dhanhq_utils-0.1.0.dist-info/RECORD
