Metadata-Version: 2.4
Name: dhanhq_utils
Version: 0.1.0
Classifier: Programming Language :: Rust
Classifier: Programming Language :: Python :: Implementation :: CPython
Classifier: Programming Language :: Python :: Implementation :: PyPy
License-File: LICENSE
Summary: A lightweight utility library for encrypting and decrypting DhanHQ Web-API payloads with minimal setup.
Home-Page: https://github.com/Indian-Algorithmic-Trading-Community/dhanhq_utils
Author-email: Shabbir Hasan <68828793+ShabbirHasan1@users.noreply.github.com>
License: Apache License 2.0
Requires-Python: >=3.9
